paddlenlp/__init__.py
paddlenlp/cli/__init__.py
paddlenlp/cli/bos_community.py
paddlenlp/cli/download.py
paddlenlp/cli/install.py
paddlenlp/cli/main.py
paddlenlp/cli/server.py
paddlenlp/cli/utils/__init__.py
paddlenlp/cli/utils/tabulate.py
paddlenlp/data/__init__.py
paddlenlp/data/blendable_dataset.py
paddlenlp/data/causal_dataset.py
paddlenlp/data/collate.py
paddlenlp/data/data_collator.py
paddlenlp/data/dist_dataloader.py
paddlenlp/data/indexed_dataset.py
paddlenlp/data/iterator.py
paddlenlp/data/sampler.py
paddlenlp/data/tokenizer.py
paddlenlp/data/vocab.py
paddlenlp/dataaug/__init__.py
paddlenlp/dataaug/base_augment.py
paddlenlp/dataaug/char.py
paddlenlp/dataaug/sentence.py
paddlenlp/dataaug/word.py
paddlenlp/datasets/__init__.py
paddlenlp/datasets/advertisegen.py
paddlenlp/datasets/bellegroup.py
paddlenlp/datasets/bq_corpus.py
paddlenlp/datasets/bstc.py
paddlenlp/datasets/c3.py
paddlenlp/datasets/cail2018_small.py
paddlenlp/datasets/cail2019_scm.py
paddlenlp/datasets/cblue.py
paddlenlp/datasets/chnsenticorp.py
paddlenlp/datasets/chnsenticorp_v2.py
paddlenlp/datasets/clue.py
paddlenlp/datasets/cmrc2018.py
paddlenlp/datasets/cnn_dailymail.py
paddlenlp/datasets/conll2002.py
paddlenlp/datasets/cote.py
paddlenlp/datasets/couplet.py
paddlenlp/datasets/dataset.py
paddlenlp/datasets/drcd.py
paddlenlp/datasets/drcd_cn.py
paddlenlp/datasets/duconv.py
paddlenlp/datasets/dureader_checklist.py
paddlenlp/datasets/dureader_qg.py
paddlenlp/datasets/dureader_robust.py
paddlenlp/datasets/dureader_yesno.py
paddlenlp/datasets/fewclue.py
paddlenlp/datasets/glue.py
paddlenlp/datasets/hyp.py
paddlenlp/datasets/imdb.py
paddlenlp/datasets/intokens_dataset.py
paddlenlp/datasets/iwslt15.py
paddlenlp/datasets/lcqmc.py
paddlenlp/datasets/lcqmc_v2.py
paddlenlp/datasets/lcsts_new.py
paddlenlp/datasets/msra_ner.py
paddlenlp/datasets/nlpcc13_evsam05_hit.py
paddlenlp/datasets/nlpcc13_evsam05_thu.py
paddlenlp/datasets/nlpcc14_sc.py
paddlenlp/datasets/nlpcc_dbqa.py
paddlenlp/datasets/paws-x.py
paddlenlp-2.8.1.dist-info/METADATA
paddlenlp-2.8.1.dist-info/WHEEL
paddlenlp-2.8.1.dist-info/entry_points.txt
paddlenlp-2.8.1.dist-info/top_level.txt
paddlenlp-2.8.1.dist-info/RECORD
