Metadata-Version: 2.1
Name: paddlenlp
Version: 2.8.1
Summary: Easy-to-use and powerful NLP library with Awesome model zoo, supporting wide-range of NLP tasks from research to industrial applications, including Neural Search, Question Answering, Information Extraction and Sentiment Analysis end-to-end system.
Home-page: https://github.com/PaddlePaddle/PaddleNLP
Author: PaddleNLP Team
Author-email: paddlenlp@baidu.com
License: Apache 2.0
Platform: UNKNOWN
Classifier: Programming Language :: Python :: 3
Classifier: Programming Language :: Python :: 3.6
Classifier: Programming Language :: Python :: 3.7
Classifier: Programming Language :: Python :: 3.8
Classifier: Programming Language :: Python :: 3.9
Classifier: License :: OSI Approved :: Apache Software License
Classifier: Operating System :: OS Independent
Requires-Python: >=3.6
Requires-Dist: jieba
Requires-Dist: colorlog
Requires-Dist: colorama
Requires-Dist: seqeval
Requires-Dist: dill <0.3.5
Requires-Dist: multiprocess <=0.70.12.2
Requires-Dist: datasets >=2.0.0
Requires-Dist: tqdm
Requires-Dist: paddlefsl
Requires-Dist: sentencepiece
Requires-Dist: huggingface-hub >=0.19.2
Requires-Dist: onnx >=1.10.0
Requires-Dist: paddle2onnx
Requires-Dist: Flask-Babel
Requires-Dist: visualdl
Requires-Dist: fastapi
Requires-Dist: uvicorn
Requires-Dist: typer
Requires-Dist: rich
Requires-Dist: safetensors
Requires-Dist: tool-helpers
Requires-Dist: aistudio-sdk >=0.1.3
Requires-Dist: jinja2
Requires-Dist: regex
Requires-Dist: protobuf >=3.20.2 ; platform_system != "Windows"
Requires-Dist: protobuf ==3.20.2 ; platform_system == "Windows"
Provides-Extra: autonlp
Requires-Dist: protobuf ==3.20.2 ; extra == 'autonlp'
Requires-Dist: pydantic ==1.10.11 ; extra == 'autonlp'
Requires-Dist: ray[tune] ==2.5.1 ; extra == 'autonlp'
Requires-Dist: hyperopt >=0.2.5 ; extra == 'autonlp'
Provides-Extra: dev
Requires-Dist: parameterized ; extra == 'dev'
Requires-Dist: sentencepiece ; extra == 'dev'
Requires-Dist: regex ; extra == 'dev'
Requires-Dist: torch >=1.5 ; extra == 'dev'
Requires-Dist: transformers ; extra == 'dev'
Requires-Dist: tool-helpers ; extra == 'dev'
Requires-Dist: fast-tokenizer-python ; extra == 'dev'
Requires-Dist: sacremoses ; extra == 'dev'
Requires-Dist: pydantic ==1.10.9 ; extra == 'dev'
Requires-Dist: modelscope ; extra == 'dev'
Requires-Dist: hyperopt ; extra == 'dev'
Requires-Dist: h5py ; extra == 'dev'
Requires-Dist: deploy ; extra == 'dev'
Requires-Dist: ray ; extra == 'dev'
Requires-Dist: loguru ; extra == 'dev'
Requires-Dist: data ; extra == 'dev'
Requires-Dist: wget ; extra == 'dev'
Requires-Dist: huggingface-hub >=0.19.2 ; extra == 'dev'
Requires-Dist: urllib3 ==1.26.2 ; extra == 'dev'
Requires-Dist: scipy ==1.9.1 ; extra == 'dev'
Requires-Dist: aiohttp ==3.8.4 ; extra == 'dev'
Requires-Dist: numpy <1.27.0,>=1.19.5 ; extra == 'dev'
Requires-Dist: h11 <0.13,>=0.11 ; extra == 'dev'
Requires-Dist: jinja2 ; extra == 'dev'
Requires-Dist: sphinx ; extra == 'dev'
Requires-Dist: sphinx-book-theme ; extra == 'dev'
Requires-Dist: readthedocs-sphinx-search ; extra == 'dev'
Requires-Dist: sphinx-rtd-theme ; extra == 'dev'
Requires-Dist: recommonmark ; extra == 'dev'
Requires-Dist: Markdown ; extra == 'dev'
Requires-Dist: sphinx-copybutton ; extra == 'dev'
Requires-Dist: sphinx-markdown-tables ; extra == 'dev'
Requires-Dist: paddlepaddle >=2.4.2 ; extra == 'dev'
Requires-Dist: paddlenlp ; extra == 'dev'
Requires-Dist: protobuf ==3.20.2 ; extra == 'dev'
Requires-Dist: pydantic ==1.10.11 ; extra == 'dev'
Requires-Dist: ray[tune] ==2.5.1 ; extra == 'dev'
Requires-Dist: hyperopt >=0.2.5 ; extra == 'dev'
Provides-Extra: docs
Requires-Dist: urllib3 ==1.26.2 ; extra == 'docs'
Requires-Dist: scipy ==1.9.1 ; extra == 'docs'
Requires-Dist: aiohttp ==3.8.4 ; extra == 'docs'
Requires-Dist: numpy <1.27.0,>=1.19.5 ; extra == 'docs'
Requires-Dist: h11 <0.13,>=0.11 ; extra == 'docs'
Requires-Dist: jinja2 ; extra == 'docs'
Requires-Dist: sphinx ; extra == 'docs'
Requires-Dist: sphinx-book-theme ; extra == 'docs'
Requires-Dist: readthedocs-sphinx-search ; extra == 'docs'
Requires-Dist: sphinx-rtd-theme ; extra == 'docs'
Requires-Dist: recommonmark ; extra == 'docs'
Requires-Dist: Markdown ; extra == 'docs'
Requires-Dist: sphinx-copybutton ; extra == 'docs'
Requires-Dist: sphinx-markdown-tables ; extra == 'docs'
Requires-Dist: paddlepaddle >=2.4.2 ; extra == 'docs'
Requires-Dist: paddlenlp ; extra == 'docs'
Provides-Extra: tests
Requires-Dist: parameterized ; extra == 'tests'
Requires-Dist: sentencepiece ; extra == 'tests'
Requires-Dist: regex ; extra == 'tests'
Requires-Dist: torch >=1.5 ; extra == 'tests'
Requires-Dist: transformers ; extra == 'tests'
Requires-Dist: tool-helpers ; extra == 'tests'
Requires-Dist: fast-tokenizer-python ; extra == 'tests'
Requires-Dist: sacremoses ; extra == 'tests'
Requires-Dist: pydantic ==1.10.9 ; extra == 'tests'
Requires-Dist: modelscope ; extra == 'tests'
Requires-Dist: hyperopt ; extra == 'tests'
Requires-Dist: h5py ; extra == 'tests'
Requires-Dist: deploy ; extra == 'tests'
Requires-Dist: ray ; extra == 'tests'
Requires-Dist: loguru ; extra == 'tests'
Requires-Dist: data ; extra == 'tests'
Requires-Dist: wget ; extra == 'tests'
Requires-Dist: huggingface-hub >=0.19.2 ; extra == 'tests'
